mlqd/__init__.py
mlqd/cnn.py
mlqd/createQD.py
mlqd/data.py
mlqd/essential_param.py
mlqd/evolution.py
mlqd/hp.py
mlqd/hyperopt_optim.py
mlqd/lic.py
mlqd/ml_dyn.py
mlqd/plot.py
mlqd/prep_input.py
mlqd/train_ml.py
mlqd/useQD.py
mlqd-1.1.1.dist-info/WHEEL
mlqd-1.1.1.dist-info/METADATA
mlqd-1.1.1.dist-info/RECORD
