Metadata-Version: 2.1
Name: mlqd
Version: 1.1.1
Summary: MLQD: A Python Package for Machine Learning-based Quantum Dissipative Dynamics
Author-email: Arif Ullah <arif@ahu.edu.cn>
Classifier: Programming Language :: Python :: 3
Classifier: License :: OSI Approved :: Apache Software License
Classifier: Operating System :: OS Independent
Requires-Dist: tensorflow>=2.12.0
Requires-Dist: scikit-learn>=1.2.2
Requires-Dist: hyperopt>=0.2.7
Requires-Dist: matplotlib>=3.7.1
Requires-Dist: mlatom==2.3.3
Project-URL: Documentation, https://github.com/Arif-PhyChem/MLQD
Project-URL: Source, https://github.com/Arif-PhyChem/MLQD
